modern_python_package/__init__.py
modern_python_package/__main__.py
modern_python_package/core.py
modern_python_package-0.0.1.dist-info/LICENSE
modern_python_package-0.0.1.dist-info/METADATA
modern_python_package-0.0.1.dist-info/WHEEL
modern_python_package-0.0.1.dist-info/top_level.txt
modern_python_package-0.0.1.dist-info/RECORD
